{
    "title": "Run compiled Haskell in the browser via Wasm",
    "epic": 16,
    "milestone": "M4: Multi-backend + Polish",
    "labels": [
        "priority:low",
        "component:backend",
        "type:feature"
    ],
    "depends_on": [
        "16-02"
    ],
    "body": "Create a demo that runs a Rusholme-compiled Haskell program in a web browser.\n\n**Deliverables:**\n- HTML page that loads the `.wasm` binary\n- JavaScript glue code to provide IO (map `putStrLn` to `console.log` or DOM output)\n- Demo: `main = putStrLn \"Hello from Rusholme!\"` running in a browser\n- Document how to build and serve the demo\n\n**Design notes:**\n- If using WASI target, a browser WASI polyfill is needed (e.g. `@aspect-build/aspect-wasi`)\n- Alternatively, target `wasm32-unknown-unknown` with custom JS imports for IO\n- This is a showcase / demo \u2014 correctness matters more than performance",
    "github_issue": 79,
    "depends_on_github": [
        78
    ]
}
